keywordextractor/keywordextractor.py
keywordextractor-2.0.0.dist-info/LICENSE
keywordextractor-2.0.0.dist-info/METADATA
keywordextractor-2.0.0.dist-info/WHEEL
keywordextractor-2.0.0.dist-info/top_level.txt
keywordextractor-2.0.0.dist-info/RECORD
